[
  {
  "author": "new message",
  "message": "a random text",
  "id": "VWMeb52b81rNWdqyd2OdW",
  "datetime": "2020-02-10T17:09:52.692Z"
  },
  {
    "author": "test 3",
    "message": "test message number 3",
    "id": "6Z8G5FIFg3hduaxVEZ-lj",
    "datetime": "2020-02-10T16:57:54.097Z"
  },
  {
    "author": "Yoda",
    "message": "May the force be with you!",
    "id": "spvh95oAVnELdeRHbsFQD",
    "datetime": "2020-02-10T16:55:21.859Z"
  },
  {
    "author": "test",
    "message": "dfsdfa",
    "id": "OXN3hiSX0Kq0a4p8C8UEs",
    "datetime": "2020-02-10T16:55:52.328Z"
  }

]